<vc:Chart xmlns:vc="clr-namespace:Visifire.Charts;assembly=Visifire.Charts"
          Theme="Theme3" AnimationType="Type4" ColorSet="Visifire2" Width="500" Height="300" View3D="True">

  <vc:Title Text="Visifire Bubble Chart" />

  <vc:DataSeries Name="2005" RenderAs="Bubble" ToolTipText="Size: #ZValue">
    <vc:DataPoint AxisLabel="2001" YValue="320" ZValue="300"/>
    <vc:DataPoint AxisLabel="2002" YValue="230" ZValue="250"/>
    <vc:DataPoint AxisLabel="2003" YValue="546" ZValue="400"/>
    <vc:DataPoint AxisLabel="2004" YValue="208" ZValue="500"/>
    <vc:DataPoint AxisLabel="2005" YValue="478" ZValue="450"/>
    <vc:DataPoint AxisLabel="2006" YValue="342" ZValue="400"/>
    <vc:DataPoint AxisLabel="2007" YValue="320" ZValue="550"/>
    <vc:DataPoint AxisLabel="2008" YValue="450" ZValue="350"/>
  </vc:DataSeries>

</vc:Chart>
